{
  "hash": "da22006e",
  "configHash": "c03e816b",
  "lockfileHash": "641120c9",
  "browserHash": "be3f6c26",
  "optimized": {
    "react": {
      "src": "../../node_modules/react/index.js",
      "file": "react.js",
      "fileHash": "a24b4233",
      "needsInterop": true
    },
    "react-dom/client": {
      "src": "../../node_modules/react-dom/client.js",
      "file": "react-dom_client.js",
      "fileHash": "527dd1c8",
      "needsInterop": true
    },
    "react-router-dom": {
      "src": "../../node_modules/react-router-dom/dist/index.js",
      "file": "react-router-dom.js",
      "fileHash": "f0fbf1cb",
      "needsInterop": false
    },
    "firebase/firestore": {
      "src": "../../node_modules/firebase/firestore/dist/esm/index.esm.js",
      "file": "firebase_firestore.js",
      "fileHash": "0054202a",
      "needsInterop": false
    },
    "lucide-react": {
      "src": "../../node_modules/lucide-react/dist/esm/lucide-react.js",
      "file": "lucide-react.js",
      "fileHash": "c0fe78e8",
      "needsInterop": false
    },
    "firebase/app": {
      "src": "../../node_modules/firebase/app/dist/esm/index.esm.js",
      "file": "firebase_app.js",
      "fileHash": "8a8be068",
      "needsInterop": false
    },
    "react-select": {
      "src": "../../node_modules/react-select/dist/react-select.esm.js",
      "file": "react-select.js",
      "fileHash": "59a7e5fd",
      "needsInterop": false
    },
    "firebase/auth": {
      "src": "../../node_modules/firebase/auth/dist/esm/index.esm.js",
      "file": "firebase_auth.js",
      "fileHash": "17503689",
      "needsInterop": false
    }
  },
  "chunks": {
    "chunk-BVONTIK6": {
      "file": "chunk-BVONTIK6.js"
    },
    "chunk-2GK3IQSO": {
      "file": "chunk-2GK3IQSO.js"
    },
    "chunk-UPJ66ANQ": {
      "file": "chunk-UPJ66ANQ.js"
    },
    "chunk-G3PMV62Z": {
      "file": "chunk-G3PMV62Z.js"
    }
  }
}